spimagine/__init__.py
spimagine/__main__.py
spimagine/startup.py
spimagine/version.py
spimagine/bin/__init__.py
spimagine/bin/spim_render.py
spimagine/bin/spimagine_gui.py
spimagine/colormaps/all_colormaps.png
spimagine/colormaps/cmap_coolwarm.png
spimagine/colormaps/cmap_fire.png
spimagine/colormaps/cmap_grays.png
spimagine/colormaps/cmap_hot.png
spimagine/colormaps/cmap_inferno.png
spimagine/colormaps/cmap_jet.png
spimagine/colormaps/cmap_magma.png
spimagine/colormaps/cmap_plasma.png
spimagine/colormaps/cmap_viridis.png
spimagine/config/__init__.py
spimagine/config/config.py
spimagine/config/loadcolormaps.py
spimagine/config/myconfigparser.py
spimagine/data/mpi_logo_80.tif
spimagine/gui/__init__.py
spimagine/gui/basic_window.py
spimagine/gui/floatslider.py
spimagine/gui/glwidget.py
spimagine/gui/gui_utils.py
spimagine/gui/imageprocessor_view.py
spimagine/gui/keyframe_view.py
spimagine/gui/mainsettings.py
spimagine/gui/mainwidget.py
spimagine/gui/mesh.py
spimagine/gui/multiple_file_dialog.py
spimagine/gui/shaders.py
spimagine/gui/shape_dtype_dialog.py
spimagine/gui/slice_view.py
spimagine/gui/volsettings.py
spimagine/gui/volshow.py
spimagine/gui/images/egg.png
spimagine/gui/images/egg_inactive.png
spimagine/gui/images/icon_backward.png
spimagine/gui/images/icon_camera.png
spimagine/gui/images/icon_camera_inactive.png
spimagine/gui/images/icon_center.jpg
spimagine/gui/images/icon_center.png
spimagine/gui/images/icon_colors.png
spimagine/gui/images/icon_distribute.png
spimagine/gui/images/icon_distribute_inactive.png
spimagine/gui/images/icon_filesave.png
spimagine/gui/images/icon_folder.png
spimagine/gui/images/icon_forward.png
spimagine/gui/images/icon_mainsettings_active.png
spimagine/gui/images/icon_mainsettings_inactive.png
spimagine/gui/images/icon_method_iso.png
spimagine/gui/images/icon_method_vol.png
spimagine/gui/images/icon_open.png
spimagine/gui/images/icon_pause.png
spimagine-0.2.6.dist-info/DESCRIPTION.rst
spimagine-0.2.6.dist-info/METADATA
spimagine-0.2.6.dist-info/RECORD
spimagine-0.2.6.dist-info/WHEEL
spimagine-0.2.6.dist-info/entry_points.txt
spimagine-0.2.6.dist-info/metadata.json
spimagine-0.2.6.dist-info/top_level.txt
