Metadata-Version: 2.0
Name: spimagine
Version: 0.2.6
Summary: OpenCL volume rendering in 3D/4D
Home-page: https://github.com/maweigert/spimagine
Author: Martin Weigert
Author-email: mweigert@mpi-cbg.de
License: BSD 3-Clause License
Platform: UNKNOWN
Classifier: Development Status :: 3 - Alpha
Classifier: Intended Audience :: Science/Research
Classifier: Topic :: Scientific/Engineering
Classifier: License :: OSI Approved :: BSD License
Classifier: Programming Language :: Python :: 2.7
Classifier: Programming Language :: Python :: 3.5
Classifier: Programming Language :: Python :: 3.6
Requires-Dist: PyOpenGL
Requires-Dist: gputools
Requires-Dist: imageio
Requires-Dist: numpy
Requires-Dist: pyopencl
Requires-Dist: scipy
Requires-Dist: sortedcontainers
Requires-Dist: ConfigParser; python_version<"3.0"
Requires-Dist: configparser; python_version>="3.2"
Requires-Dist: pyqt5; python_version>="3.2"
